dictremapper
