Metadata-Version: 1.1
Name: dictremapper
Version: 0.0.2
Summary: remapping dict
Home-page: https://github.com/podhmo/dictremapper
Author: podhmo
Author-email: UNKNOWN
License: mit
Keywords: dict,remapping,structure
Platform: UNKNOWN
Classifier: Programming Language :: Python
Classifier: Programming Language :: Python :: Implementation :: CPython
